LICENSE
README.md
setup.py
PySide6_Fluent_Widgets_Fix.egg-info/PKG-INFO
PySide6_Fluent_Widgets_Fix.egg-info/SOURCES.txt
PySide6_Fluent_Widgets_Fix.egg-info/dependency_links.txt
PySide6_Fluent_Widgets_Fix.egg-info/requires.txt
PySide6_Fluent_Widgets_Fix.egg-info/top_level.txt
qfluentwidgets/__init__.py
qfluentwidgets/_rc/__init__.py
qfluentwidgets/_rc/resource.py
qfluentwidgets/common/__init__.py
qfluentwidgets/common/animation.py
qfluentwidgets/common/auto_wrap.py
qfluentwidgets/common/color.py
qfluentwidgets/common/config.py
qfluentwidgets/common/enum.py
qfluentwidgets/common/exception_handler.py
qfluentwidgets/common/font.py
qfluentwidgets/common/icon.py
qfluentwidgets/common/image_utils.py
qfluentwidgets/common/overload.py
qfluentwidgets/common/router.py
qfluentwidgets/common/screen.py
qfluentwidgets/common/smooth_scroll.py
qfluentwidgets/common/style_sheet.py
qfluentwidgets/common/translator.py
qfluentwidgets/components/__init__.py
qfluentwidgets/components/date_time/__init__.py
qfluentwidgets/components/date_time/calendar_picker.py
qfluentwidgets/components/date_time/calendar_view.py
qfluentwidgets/components/date_time/date_picker.py
qfluentwidgets/components/date_time/picker_base.py
qfluentwidgets/components/date_time/time_picker.py
qfluentwidgets/components/dialog_box/__init__.py
qfluentwidgets/components/dialog_box/color_dialog.py
qfluentwidgets/components/dialog_box/dialog.py
qfluentwidgets/components/dialog_box/folder_list_dialog.py
qfluentwidgets/components/dialog_box/mask_dialog_base.py
qfluentwidgets/components/dialog_box/message_box_base.py
qfluentwidgets/components/dialog_box/message_dialog.py
qfluentwidgets/components/layout/__init__.py
qfluentwidgets/components/layout/expand_layout.py
qfluentwidgets/components/layout/flow_layout.py
qfluentwidgets/components/layout/v_box_layout.py
qfluentwidgets/components/material/__init__.py
qfluentwidgets/components/material/acrylic_combo_box.py
qfluentwidgets/components/material/acrylic_flyout.py
qfluentwidgets/components/material/acrylic_line_edit.py
qfluentwidgets/components/material/acrylic_menu.py
qfluentwidgets/components/material/acrylic_tool_tip.py
qfluentwidgets/components/material/acrylic_widget.py
qfluentwidgets/components/navigation/__init__.py
