Metadata-Version: 2.1
Name: PySide6-Fluent-Widgets-Fix
Version: 1.5.7
Summary: A fluent design widgets library based on PySide6
Home-page: https://qfluentwidgets.com
Author: zhiyiYo
Author-email: shokokawaii@outlook.com
License: GPLv3
Project-URL: Documentation, https://qfluentwidgets.com/
Project-URL: Source Code, https://github.com/zhiyiYo/PyQt-Fluent-Widgets/tree/PySide6
Project-URL: Bug Tracker, https://github.com/zhiyiYo/PyQt-Fluent-Widgets/issues
Keywords: pyside6 fluent widgets
Platform: UNKNOWN
Classifier: Programming Language :: Python :: 3
Classifier: License :: OSI Approved :: GNU General Public License v3 (GPLv3)
Classifier: Operating System :: OS Independent
Provides-Extra: full
License-File: LICENSE
